{"chunk_definitions":[{"row":11,"row_count":1,"visible":true,"expansion_state":0,"options":{"engine":"r","label":"setup","include":false,"dev":"png"},"document_id":"81356DFB","chunk_id":"csetup_chunk","chunk_label":"setup"},{"row":63,"row_count":1,"visible":true,"expansion_state":0,"options":{"engine":"r","label":"data-generation","dev":"png"},"document_id":"81356DFB","chunk_id":"cy5n95l9eub23","chunk_label":"data-generation"},{"row":90,"row_count":1,"visible":true,"expansion_state":0,"options":{"engine":"r","label":"trajectory-plot","dev":"png"},"document_id":"81356DFB","chunk_id":"c9dr49gl9cli8","chunk_label":"trajectory-plot"},{"row":121,"row_count":1,"visible":true,"expansion_state":0,"options":{"engine":"r","label":"cvd-linkage-plot","dev":"png"},"document_id":"81356DFB","chunk_id":"c29wbez28ze9p","chunk_label":"cvd-linkage-plot"},{"row":137,"row_count":1,"visible":true,"expansion_state":0,"options":{"engine":"r","label":"statistical-model","dev":"png"},"document_id":"81356DFB","chunk_id":"c8viyyihbqjyi","chunk_label":"statistical-model"}],"doc_write_time":1778975994,"working_dir":null,"default_chunk_options":{"echo":true,"message":false,"warning":false,"fig.width":10.0,"fig.height":6.0},"chunk_rendered_width":563}